AUTHORS
INSTALL
LICENSE
MANIFEST.in
NOTICE
README
requirements.txt
setup.cfg
setup.py
docs/Makefile
docs/conf.py
docs/configuration.rst
docs/faq.rst
docs/index.rst
docs/installation.rst
docs/introduction.rst
docs/make.bat
docs/usage.rst
src/context_extras/__init__.py
src/context_extras/context_processors.py
src/context_extras/models.py
src/django_context_extras.egg-info/PKG-INFO
src/django_context_extras.egg-info/SOURCES.txt
src/django_context_extras.egg-info/dependency_links.txt
src/django_context_extras.egg-info/top_level.txt